mp1b/mp1_b/mp1_b.srcs/sources_1/new/mp1_b.v
`timescale 1ns / 1ps
//////////////////////////////////////////////////////////////////////////////////
// Company: 
// Engineer: 
// 
// Create Date: 09/02/2025 07:11:17 PM
// Design Name: 
// Module Name: mp1_b
// Project Name: 
// Target Devices: 
// Tool Versions: 
// Description: 
// 
// Dependencies: 
// 
// Revision:
// Revision 0.01 - File Created
// Additional Comments:
// 
//////////////////////////////////////////////////////////////////////////////////

// Switch to LED Display System with Multiple Modes
// Maps 2 switches to 4 LEDs with different display modes

module switch_led_modes(
    input wire clk,           // System clock
    input wire [1:0] sw,      // Two slide switches
    input wire [3:0] btn,     // Four push buttons
    output reg [3:0] led      // Four regular LEDs (LD0-LD3)
);

    // Internal signals
    reg [1:0] current_mode;   // Current display mode (0-3)
    reg [3:0] base_state;     // Base LED pattern from switch mapping
    reg [3:0] displayed_state; // Final LED pattern after mode processing
    
    // Button edge detection registers
    reg [3:0] btn_prev;       // Previous button state
    wire [3:0] btn_pressed;   // Button press detected (rising edge)
    
    // Detect button press (rising edge)
    assign btn_pressed = btn & ~btn_prev;
    
    // Update previous button state
    always @(posedge clk) begin
        btn_prev <= btn;
    end
    
    // Mode selection based on button press
    always @(posedge clk) begin
        if (btn_pressed[0])
            current_mode <= 2'b00;  // Mode 0
        else if (btn_pressed[1])
            current_mode <= 2'b01;  // Mode 1
        else if (btn_pressed[2])
            current_mode <= 2'b10;  // Mode 2
        else if (btn_pressed[3])
            current_mode <= 2'b11;  // Mode 3
        // Note: If no button pressed, mode remains unchanged
    end
    
    // Map switches to base LED state
    always @(*) begin
        case (sw)
            2'b00: base_state = 4'b0001;  // SW=00 → 0001
            2'b01: base_state = 4'b0011;  // SW=01 → 0011
            2'b10: base_state = 4'b0111;  // SW=10 → 0111
            2'b11: base_state = 4'b1111;  // SW=11 → 1111
            default: base_state = 4'b0001; // Default case
        endcase
    end
    
    // Apply mode transformation to base state
    always @(*) begin
        case (current_mode)
            2'b00: // Mode 0: Display state as-is
                displayed_state = base_state;
                
            2'b01: // Mode 1: Logical shift right by 2
                displayed_state = base_state >> 2;
                
            2'b10: // Mode 2: Circular shift left by 3
                displayed_state = {base_state[0], base_state[3:1]};
                // Note: Circular left by 3 is same as circular right by 1 for 4 bits
                
            2'b11: // Mode 3: Bitwise invert
                displayed_state = ~base_state;
                
            default:
                displayed_state = base_state;
        endcase
    end
    
    // Output the displayed state to LEDs
    always @(posedge clk) begin
        led <= displayed_state;
    end
    
endmodule

mp1b/mp1_b/mp1_b.srcs/sim_1/new/mp1_b_tb.v
`timescale 1ns / 1ps
//////////////////////////////////////////////////////////////////////////////////
// Company: 
// Engineer: 
// 
// Create Date: 09/02/2025 07:30:57 PM
// Design Name: 
// Module Name: mp1_b_tb
// Project Name: 
// Target Devices: 
// Tool Versions: 
// Description: 
// 
// Dependencies: 
// 
// Revision:
// Revision 0.01 - File Created
// Additional Comments:
// 
//////////////////////////////////////////////////////////////////////////////////

`timescale 1ns / 1ps

module switch_led_modes_tb;

    // Inputs
    reg clk;
    reg [1:0] sw;
    reg [3:0] btn;
    
    // Outputs
    wire [3:0] led;
    
    // Expected values for verification
    reg [3:0] expected_led;
    integer error_count = 0;
    integer test_count = 0;
    
    // Instantiate the Unit Under Test (UUT)
    switch_led_modes uut (
        .clk(clk),
        .sw(sw),
        .btn(btn),
        .led(led)
    );
    
    // Clock generation - 10ns period (100MHz)
    initial begin
        clk = 0;
        forever #5 clk = ~clk;
    end
    
    // Task to press and release a button
    task press_button;
        input [1:0] button_num;
        begin
            btn = 4'b0000;
            #10;
            btn[button_num] = 1'b1;  // Press button
            #20;  // Hold for 2 clock cycles
            btn[button_num] = 1'b0;  // Release button
            #20;  // Wait for processing
        end
    endtask
    
    // Task to test a specific switch configuration in all modes
    task test_switch_config;
        input [1:0] switch_val;
        input [3:0] base_pattern;
        begin
            sw = switch_val;
            #10;
            
            $display("\n  Testing SW=%b (base pattern=%b)", switch_val, base_pattern);
            
            // Test Mode 0: Display as-is
            press_button(0);
            expected_led = base_pattern;
            #10;
            test_count = test_count + 1;
            if (led !== expected_led) begin
                $display("    ERROR Mode 0: LED=%b, Expected=%b", led, expected_led);
                error_count = error_count + 1;
            end else begin
                $display("    PASS Mode 0: LED=%b", led);
            end
            
            // Test Mode 1: Logical shift right by 2
            press_button(1);
            expected_led = base_pattern >> 2;
            #10;
            test_count = test_count + 1;
            if (led !== expected_led) begin
                $display("    ERROR Mode 1: LED=%b, Expected=%b", led, expected_led);
                error_count = error_count + 1;
            end else begin
                $display("    PASS Mode 1: LED=%b (>>2)", led);
            end
            
            // Test Mode 2: Circular shift left by 3 (same as right by 1 for 4 bits)
            press_button(2);
            expected_led = {base_pattern[0], base_pattern[3:1]};
            #10;
            test_count = test_count + 1;
            if (led !== expected_led) begin
                $display("    ERROR Mode 2: LED=%b, Expected=%b", led, expected_led);
                error_count = error_count + 1;
            end else begin
                $display("    PASS Mode 2: LED=%b (circular left 3)", led);
            end
            
            // Test Mode 3: Bitwise invert
            press_button(3);
            expected_led = ~base_pattern;
            #10;
            test_count = test_count + 1;
            if (led !== expected_led) begin
                $display("    ERROR Mode 3: LED=%b, Expected=%b", led, expected_led);
                error_count = error_count + 1;
            end else begin
                $display("    PASS Mode 3: LED=%b (inverted)", led);
            end
        end
    endtask
    
    // Main test sequence
    initial begin
        // Initialize
        sw = 2'b00;
        btn = 4'b0000;
        
        // Create VCD file for waveform viewing
        $dumpfile("switch_led_modes_tb.vcd");
        $dumpvars(0, switch_led_modes_tb);
        
        // Display header
        $display("\n====================================");
        $display("  Switch-LED Modes System Testbench");
        $display("====================================");
        
        // Wait for initial stabilization
        #100;
        
        // Test all switch combinations
        $display("\n--- Testing All Switch Combinations ---");
        
        test_switch_config(2'b00, 4'b0001);  // SW=00 → 0001
        test_switch_config(2'b01, 4'b0011);  // SW=01 → 0011
        test_switch_config(2'b10, 4'b0111);  // SW=10 → 0111
        test_switch_config(2'b11, 4'b1111);  // SW=11 → 1111
        
        // Test mode persistence (mode should stay when switch changes)
        $display("\n--- Testing Mode Persistence ---");
        press_button(2);  // Set to Mode 2
        sw = 2'b00;  // Base pattern will be 0001
        #20;
        expected_led = 4'b1000;  // 0001 circular left by 3
        if (led !== expected_led) begin
            $display("  ERROR: Mode didn't persist. LED=%b, Expected=%b", led, expected_led);
            error_count = error_count + 1;
        end else begin
            $display("  PASS: Mode 2 persisted after switch change. LED=%b", led);
        end
        test_count = test_count + 1;
        
        sw = 2'b11;  // Change switch, mode should remain
        #20;
        expected_led = 4'b1111;  // 1111 circular left by 3 = 1111
        if (led !== expected_led) begin
            $display("  ERROR: Mode didn't persist. LED=%b, Expected=%b", led, expected_led);
            error_count = error_count + 1;
        end else begin
            $display("  PASS: Mode 2 still active. LED=%b", led);
        end
        test_count = test_count + 1;
        
        // Test rapid button presses
        $display("\n--- Testing Rapid Mode Changes ---");
        sw = 2'b10;  // Base pattern 0111
        press_button(0);
        #10;
        $display("  Mode 0: LED=%b", led);
        press_button(1);
        #10;
        $display("  Mode 1: LED=%b", led);
        press_button(2);
        #10;
        $display("  Mode 2: LED=%b", led);
        press_button(3);
        #10;
        $display("  Mode 3: LED=%b", led);
        
        // Detailed example calculations
        $display("\n--- Detailed Mode Transformations ---");
        sw = 2'b10;  // Base: 0111
        $display("  Switch state: %b → Base pattern: 0111", sw);
        
        press_button(0);
        #20;
        $display("    Mode 0 (as-is):           0111 → %b", led);
        
        press_button(1);
        #20;
        $display("    Mode 1 (>>2):             0111 → %b", led);
        
        press_button(2);
        #20;
        $display("    Mode 2 (circular left 3): 0111 → %b", led);
        
        press_button(3);
        #20;
        $display("    Mode 3 (invert):          0111 → %b", led);
        
        // Final summary
        #100;
        $display("\n====================================");
        $display("         Testbench Summary");
        $display("====================================");
        $display("  Total Tests: %0d", test_count);
        $display("  Passed: %0d", test_count - error_count);
        $display("  Failed: %0d", error_count);
        $display("====================================");
        
        if (error_count == 0) begin
            $display("\n*** ALL TESTS PASSED! ***\n");
        end else begin
            $display("\n*** %0d TESTS FAILED ***\n", error_count);
        end
        
        $finish;
    end
    
    // Monitor for debugging
    initial begin
        $monitor("Time=%0t: clk=%b sw=%b btn=%b mode=%b led=%b", 
                 $time, clk, sw, btn, uut.current_mode, led);
    end

endmodule

mp1b/mp1_b/mp1_b.sim/sim_1/behav/xsim/switch_led_modes_tb.vcd
$date
   Mon Sep  8 18:52:29 2025
$end

$version
  2025.1.0
  $dumpfile ("switch_led_modes_tb.vcd") 
$end

$timescale
  1ps
$end

$scope module switch_led_modes_tb $end
$var reg 1 ! clk $end
$var reg 2 " sw [1:0] $end
$var reg 4 # btn [3:0] $end
$var wire 4 $ led [3:0] $end
$var reg 4 % expected_led [3:0] $end
$var integer 32 & error_count [31:0] $end
$var integer 32 ' test_count [31:0] $end
$scope module uut $end
$var wire 1 ( clk $end
$var wire 2 ) sw [1:0] $end
$var wire 4 * btn [3:0] $end
$var reg 4 + led [3:0] $end
$var reg 2 , current_mode [1:0] $end
$var reg 4 - base_state [3:0] $end
$var reg 4 . displayed_state [3:0] $end
$var reg 4 / btn_prev [3:0] $end
$var wire 4 0 btn_pressed [3:0] $end
$upscope $end
$scope task press_button $end
$var reg 2 1 button_num [1:0] $end
$upscope $end
$scope task test_switch_config $end
$var reg 2 2 switch_val [1:0] $end
$var reg 4 3 base_pattern [3:0] $end
$upscope $end
$upscope $end
$enddefinitions $end

#0
$dumpvars
0!
b0 "
b0 #
bx $
bx %
b0 &
b0 '
0(
b0 )
b0 *
bx +
bx ,
b1 -
b1 .
bx /
b0 0
bx 1
bx 2
bx 3
$end

#5000
1!
b1 $
1(
b1 +
b0 /

#10000
0!
0(

#15000
1!
1(

#20000
0!
0(

#25000
1!
1(

#30000
0!
0(

#35000
1!
1(

#40000
0!
0(

#45000
1!
1(

#50000
0!
0(

#55000
1!
1(

#60000
0!
0(

#65000
1!
1(

#70000
0!
0(

#75000
1!
1(

#80000
0!
0(

#85000
1!
1(

#90000
0!
0(

#95000
1!
1(

#100000
0!
0(
b0 2
b1 3

#105000
1!
1(

#110000
0!
0(
b0 1

#115000
1!
1(

#120000
0!
b1 #
0(
b1 *
b1 0

#125000
1!
1(
b0 ,
b1 /
b0 0

#130000
0!
0(

#135000
1!
1(

#140000
0!
b0 #
0(
b0 *

#145000
1!
1(
b0 /

#150000
0!
0(

#155000
1!
1(

#160000
0!
b1 %
0(

#165000
1!
1(

#170000
0!
b1 '
0(
b1 1

#175000
1!
1(

#180000
0!
b10 #
0(
b10 *
b10 0

#185000
1!
1(
b1 ,
b0 .
b10 /
b0 0

#190000
0!
0(

#195000
1!
b0 $
1(
b0 +

#200000
0!
b0 #
0(
b0 *

#205000
1!
1(
b0 /

#210000
0!
0(

#215000
1!
1(

#220000
0!
b0 %
0(

#225000
1!
1(

#230000
0!
b10 '
0(
b10 1

#235000
1!
1(

#240000
0!
b100 #
0(
b100 *
b100 0

#245000
1!
1(
b10 ,
b1000 .
b100 /
b0 0

#250000
0!
0(

#255000
1!
b1000 $
1(
b1000 +

#260000
0!
b0 #
0(
b0 *

#265000
1!
1(
b0 /

#270000
0!
0(

#275000
1!
1(

#280000
0!
b1000 %
0(

#285000
1!
1(

#290000
0!
b11 '
0(
b11 1

#295000
1!
1(

#300000
0!
b1000 #
0(
b1000 *
b1000 0

#305000
1!
1(
b11 ,
b1110 .
b1000 /
b0 0

#310000
0!
0(

#315000
1!
b1110 $
1(
b1110 +

#320000
0!
b0 #
0(
b0 *

#325000
1!
1(
b0 /

#330000
0!
0(

#335000
1!
1(

#340000
0!
b1110 %
0(

#345000
1!
1(

#350000
0!
b1 "
b100 '
0(
b1 )
b11 -
b1100 .
b1 2
b11 3

#355000
1!
b1100 $
1(
b1100 +

#360000
0!
0(
b0 1

#365000
1!
1(

#370000
0!
b1 #
0(
b1 *
b1 0

#375000
1!
1(
b0 ,
b11 .
b1 /
b0 0

#380000
0!
0(

#385000
1!
b11 $
1(
b11 +

#390000
0!
b0 #
0(
b0 *

#395000
1!
1(
b0 /

#400000
0!
0(

#405000
1!
1(

#410000
0!
b11 %
0(

#415000
1!
1(

#420000
0!
b101 '
0(
b1 1

#425000
1!
1(

#430000
0!
b10 #
0(
b10 *
b10 0

#435000
1!
1(
b1 ,
b0 .
b10 /
b0 0

#440000
0!
0(

#445000
1!
b0 $
1(
b0 +

#450000
0!
b0 #
0(
b0 *

#455000
1!
1(
b0 /

#460000
0!
0(

#465000
1!
1(

#470000
0!
b0 %
0(

#475000
1!
1(

#480000
0!
b110 '
0(
b10 1

#485000
1!
1(

#490000
0!
b100 #
0(
b100 *
b100 0

#495000
1!
1(
b10 ,
b1001 .
b100 /
b0 0

#500000
0!
0(

#505000
1!
b1001 $
1(
b1001 +

#510000
0!
b0 #
0(
b0 *

#515000
1!
1(
b0 /

#520000
0!
0(

#525000
1!
1(

#530000
0!
b1001 %
0(

#535000
1!
1(

#540000
0!
b111 '
0(
b11 1

#545000
1!
1(

#550000
0!
b1000 #
0(
b1000 *
b1000 0

#555000
1!
1(
b11 ,
b1100 .
b1000 /
b0 0

#560000
0!
0(

#565000
1!
b1100 $
1(
b1100 +

#570000
0!
b0 #
0(
b0 *

#575000
1!
1(
b0 /

#580000
0!
0(

#585000
1!
1(

#590000
0!
b1100 %
0(

#595000
1!
1(

#600000
0!
b10 "
b1000 '
0(
b10 )
b111 -
b1000 .
b10 2
b111 3

#605000
1!
b1000 $
1(
b1000 +

#610000
0!
0(
b0 1

#615000
1!
1(

#620000
0!
b1 #
0(
b1 *
b1 0

#625000
1!
1(
b0 ,
b111 .
b1 /
b0 0

#630000
0!
0(

#635000
1!
b111 $
1(
b111 +

#640000
0!
b0 #
0(
b0 *

#645000
1!
1(
b0 /

#650000
0!
0(

#655000
1!
1(

#660000
0!
b111 %
0(

#665000
1!
1(

#670000
0!
b1001 '
0(
b1 1

#675000
1!
1(

#680000
0!
b10 #
0(
b10 *
b10 0

#685000
1!
1(
b1 ,
b1 .
b10 /
b0 0

#690000
0!
0(

#695000
1!
b1 $
1(
b1 +

#700000
0!
b0 #
0(
b0 *

#705000
1!
1(
b0 /

#710000
0!
0(

#715000
1!
1(

#720000
0!
b1 %
0(

#725000
1!
1(

#730000
0!
b1010 '
0(
b10 1

#735000
1!
1(

#740000
0!
b100 #
0(
b100 *
b100 0

#745000
1!
1(
b10 ,
b1011 .
b100 /
b0 0

#750000
0!
0(

#755000
1!
b1011 $
1(
b1011 +

#760000
0!
b0 #
0(
b0 *

#765000
1!
1(
b0 /

#770000
0!
0(

#775000
1!
1(

#780000
0!
b1011 %
0(

#785000
1!
1(

#790000
0!
b1011 '
0(
b11 1

#795000
1!
1(

#800000
0!
b1000 #
0(
b1000 *
b1000 0

#805000
1!
1(
b11 ,
b1000 .
b1000 /
b0 0

#810000
0!
0(

#815000
1!
b1000 $
1(
b1000 +

#820000
0!
b0 #
0(
b0 *

#825000
1!
1(
b0 /

#830000
0!
0(

#835000
1!
1(

#840000
0!
b1000 %
0(

#845000
1!
1(

#850000
0!
b11 "
b1100 '
0(
b11 )
b1111 -
b0 .
b11 2
b1111 3

#855000
1!
b0 $
1(
b0 +

#860000
0!
0(
b0 1

#865000
1!
1(

#870000
0!
b1 #
0(
b1 *
b1 0

#875000
1!
1(
b0 ,
b1111 .
b1 /
b0 0

#880000
0!
0(

#885000
1!
b1111 $
1(
b1111 +

#890000
0!
b0 #
0(
b0 *

#895000
1!
1(
b0 /

#900000
0!
0(

#905000
1!
1(

#910000
0!
b1111 %
0(

#915000
1!
1(

#920000
0!
b1101 '
0(
b1 1

#925000
1!
1(

#930000
0!
b10 #
0(
b10 *
b10 0

#935000
1!
1(
b1 ,
b11 .
b10 /
b0 0

#940000
0!
0(

#945000
1!
b11 $
1(
b11 +

#950000
0!
b0 #
0(
b0 *

#955000
1!
1(
b0 /

#960000
0!
0(

#965000
1!
1(

#970000
0!
b11 %
0(

#975000
1!
1(

#980000
0!
b1110 '
0(
b10 1

#985000
1!
1(

#990000
0!
b100 #
0(
b100 *
b100 0

#995000
1!
1(
b10 ,
b1111 .
b100 /
b0 0

#1000000
0!
0(

#1005000
1!
b1111 $
1(
b1111 +

#1010000
0!
b0 #
0(
b0 *

#1015000
1!
1(
b0 /

#1020000
0!
0(

#1025000
1!
1(

#1030000
0!
b1111 %
0(

#1035000
1!
1(

#1040000
0!
b1111 '
0(
b11 1

#1045000
1!
1(

#1050000
0!
b1000 #
0(
b1000 *
b1000 0

#1055000
1!
1(
b11 ,
b0 .
b1000 /
b0 0

#1060000
0!
0(

#1065000
1!
b0 $
1(
b0 +

#1070000
0!
b0 #
0(
b0 *

#1075000
1!
1(
b0 /

#1080000
0!
0(

#1085000
1!
1(

#1090000
0!
b0 %
0(

#1095000
1!
1(

#1100000
0!
b10000 '
0(
b10 1

#1105000
1!
1(

#1110000
0!
b100 #
0(
b100 *
b100 0

#1115000
1!
1(
b10 ,
b1111 .
b100 /
b0 0

#1120000
0!
0(

#1125000
1!
b1111 $
1(
b1111 +

#1130000
0!
b0 #
0(
b0 *

#1135000
1!
1(
b0 /

#1140000
0!
0(

#1145000
1!
1(

#1150000
0!
b0 "
0(
b0 )
b1 -
b1000 .

#1155000
1!
b1000 $
1(
b1000 +

#1160000
0!
0(

#1165000
1!
1(

#1170000
0!
b11 "
b1000 %
b10001 '
0(
b11 )
b1111 -
b1111 .

#1175000
1!
b1111 $
1(
b1111 +

#1180000
0!
0(

#1185000
1!
1(

#1190000
0!
b10 "
b1111 %
b10010 '
0(
b10 )
b111 -
b1011 .
b0 1

#1195000
1!
b1011 $
1(
b1011 +

#1200000
0!
b1 #
0(
b1 *
b1 0

#1205000
1!
1(
b0 ,
b111 .
b1 /
b0 0

#1210000
0!
0(

#1215000
1!
b111 $
1(
b111 +

#1220000
0!
b0 #
0(
b0 *

#1225000
1!
1(
b0 /

#1230000
0!
0(

#1235000
1!
1(

#1240000
0!
0(

#1245000
1!
1(

#1250000
0!
0(
b1 1

#1255000
1!
1(

#1260000
0!
b10 #
0(
b10 *
b10 0

#1265000
1!
1(
b1 ,
b1 .
b10 /
b0 0

#1270000
0!
0(

#1275000
1!
b1 $
1(
b1 +

#1280000
0!
b0 #
0(
b0 *

#1285000
1!
1(
b0 /

#1290000
0!
0(

#1295000
1!
1(

#1300000
0!
0(

#1305000
1!
1(

#1310000
0!
0(
b10 1

#1315000
1!
1(

#1320000
0!
b100 #
0(
b100 *
b100 0

#1325000
1!
1(
b10 ,
b1011 .
b100 /
b0 0

#1330000
0!
0(

#1335000
1!
b1011 $
1(
b1011 +

#1340000
0!
b0 #
0(
b0 *

#1345000
1!
1(
b0 /

#1350000
0!
0(

#1355000
1!
1(

#1360000
0!
0(

#1365000
1!
1(

#1370000
0!
0(
b11 1

#1375000
1!
1(

#1380000
0!
b1000 #
0(
b1000 *
b1000 0

#1385000
1!
1(
b11 ,
b1000 .
b1000 /
b0 0

#1390000
0!
0(

#1395000
1!
b1000 $
1(
b1000 +

#1400000
0!
b0 #
0(
b0 *

#1405000
1!
1(
b0 /

#1410000
0!
0(

#1415000
1!
1(

#1420000
0!
0(

#1425000
1!
1(

#1430000
0!
0(
b0 1

#1435000
1!
1(

#1440000
0!
b1 #
0(
b1 *
b1 0

#1445000
1!
1(
b0 ,
b111 .
b1 /
b0 0

#1450000
0!
0(

#1455000
1!
b111 $
1(
b111 +

#1460000
0!
b0 #
0(
b0 *

#1465000
1!
1(
b0 /

#1470000
0!
0(

#1475000
1!
1(

#1480000
0!
0(

#1485000
1!
1(

#1490000
0!
0(

#1495000
1!
1(

#1500000
0!
0(
b1 1

#1505000
1!
1(

#1510000
0!
b10 #
0(
b10 *
b10 0

#1515000
1!
1(
b1 ,
b1 .
b10 /
b0 0

#1520000
0!
0(

#1525000
1!
b1 $
1(
b1 +

#1530000
0!
b0 #
0(
b0 *

#1535000
1!
1(
b0 /

#1540000
0!
0(

#1545000
1!
1(

#1550000
0!
0(

#1555000
1!
1(

#1560000
0!
0(

#1565000
1!
1(

#1570000
0!
0(
b10 1

#1575000
1!
1(

#1580000
0!
b100 #
0(
b100 *
b100 0

#1585000
1!
1(
b10 ,
b1011 .
b100 /
b0 0

#1590000
0!
0(

#1595000
1!
b1011 $
1(
b1011 +

#1600000
0!
b0 #
0(
b0 *

#1605000
1!
1(
b0 /

#1610000
0!
0(

#1615000
1!
1(

#1620000
0!
0(

#1625000
1!
1(

#1630000
0!
0(

#1635000
1!
1(

#1640000
0!
0(
b11 1

#1645000
1!
1(

#1650000
0!
b1000 #
0(
b1000 *
b1000 0

#1655000
1!
1(
b11 ,
b1000 .
b1000 /
b0 0

#1660000
0!
0(

#1665000
1!
b1000 $
1(
b1000 +

#1670000
0!
b0 #
0(
b0 *

#1675000
1!
1(
b0 /

